invenio_search_ui/__init__.py
invenio_search_ui/config.py
invenio_search_ui/ext.py
invenio_search_ui/searchconfig.py
invenio_search_ui/views.py
invenio_search_ui/webpack.py
invenio_search_ui/assets/bootstrap3/js/invenio_search_ui/app.js
invenio_search_ui/assets/bootstrap3/scss/invenio_search_ui/search.scss
invenio_search_ui/assets/semantic-ui/js/invenio_search_ui/app.js
invenio_search_ui/assets/semantic-ui/js/invenio_search_ui/defaultComponents.js
invenio_search_ui/assets/semantic-ui/js/invenio_search_ui/index.js
invenio_search_ui/assets/semantic-ui/js/invenio_search_ui/util.js
invenio_search_ui/assets/semantic-ui/js/invenio_search_ui/components/InvenioSearchPagination.js
invenio_search_ui/assets/semantic-ui/js/invenio_search_ui/components/MultipleOptionsSearchBar.js
invenio_search_ui/assets/semantic-ui/js/invenio_search_ui/components/Results.js
invenio_search_ui/assets/semantic-ui/js/invenio_search_ui/components/ResultsGridItem.js
invenio_search_ui/assets/semantic-ui/js/invenio_search_ui/components/ResultsListItem.js
invenio_search_ui/assets/semantic-ui/js/invenio_search_ui/components/SearchApp.js
invenio_search_ui/assets/semantic-ui/js/invenio_search_ui/components/SearchAppFacets.js
invenio_search_ui/assets/semantic-ui/js/invenio_search_ui/components/SearchAppResultsPane.js
invenio_search_ui/assets/semantic-ui/js/invenio_search_ui/components/SearchBar.js
invenio_search_ui/assets/semantic-ui/js/invenio_search_ui/components/SearchDropdowns.js
invenio_search_ui/assets/semantic-ui/js/invenio_search_ui/components/SearchFilters.js
invenio_search_ui/assets/semantic-ui/js/invenio_search_ui/components/context.js
invenio_search_ui/assets/semantic-ui/js/invenio_search_ui/components/index.js
invenio_search_ui/assets/semantic-ui/js/invenio_search_ui/components/common/facets.js
invenio_search_ui/assets/semantic-ui/translations/invenio_search_ui/i18next.js
invenio_search_ui/assets/semantic-ui/translations/invenio_search_ui/package.json
invenio_search_ui-4.1.5.dist-info/licenses/AUTHORS.rst
invenio_search_ui-4.1.5.dist-info/licenses/LICENSE
invenio_search_ui-4.1.5.dist-info/METADATA
invenio_search_ui-4.1.5.dist-info/WHEEL
invenio_search_ui-4.1.5.dist-info/entry_points.txt
invenio_search_ui-4.1.5.dist-info/top_level.txt
invenio_search_ui-4.1.5.dist-info/RECORD
