Metadata-Version: 2.4
Name: invenio-search-ui
Version: 4.1.5
Summary: UI for Invenio-Search.
Home-page: https://github.com/inveniosoftware/invenio-search-ui
Author: CERN
Author-email: info@inveniosoftware.org
License: MIT
Keywords: invenio search ui
Platform: any
Classifier: Development Status :: 5 - Production/Stable
Requires-Python: >=3.7
License-File: LICENSE
License-File: AUTHORS.rst
Requires-Dist: Babel>=2.8
Requires-Dist: invenio-assets<5.0.0,>=4.0.0
Requires-Dist: invenio-base<3.0.0,>=2.0.0
Requires-Dist: invenio-i18n<4.0.0,>=3.0.0
Provides-Extra: tests
Requires-Dist: pytest-black-ng>=0.4.0; extra == "tests"
Requires-Dist: invenio-db<3.0.0,>=2.0.0; extra == "tests"
Requires-Dist: invenio-records<4.0.0,>=3.0.0; extra == "tests"
Requires-Dist: pytest-invenio<4.0.0,>=3.0.0; extra == "tests"
Requires-Dist: sphinx>=4.5; extra == "tests"
Dynamic: license-file
